segzoo/Snakefile
segzoo/__init__.py
segzoo/create_aggregation_results.py
segzoo/create_gene_biotype_gtfs.py
segzoo/create_gmtk_results.py
segzoo/create_nucleotide_results.py
segzoo/create_overlap_repeatmasker_results.py
segzoo/create_overlap_results.py
segzoo/create_phastcons_results.py
segzoo/create_repeatmasker_results.py
segzoo/gene_biotypes.py
segzoo/main.py
segzoo/version.py
segzoo/visualization.py
segzoo-1.0.13.dist-info/LICENSE.txt
segzoo-1.0.13.dist-info/METADATA
segzoo-1.0.13.dist-info/WHEEL
segzoo-1.0.13.dist-info/entry_points.txt
segzoo-1.0.13.dist-info/top_level.txt
segzoo-1.0.13.dist-info/RECORD
