Metadata-Version: 2.1
Name: segzoo
Version: 1.0.13
Summary: System for turnkey analysis of semi-automated genome annotations
Home-page: https://github.com/hoffmangroup/segzoo
Author: Mickael Mendez
Author-email: mickael.mendez@mail.utoronto.ca
Classifier: Development Status :: 3 - Alpha
Classifier: Topic :: Scientific/Engineering :: Bio-Informatics
Classifier: License :: OSI Approved :: GNU General Public License v2 (GPLv2)
Classifier: Programming Language :: Python :: 3.7
Classifier: Programming Language :: Python :: 3.8
Requires-Python: >=3.7
License-File: LICENSE.txt
Requires-Dist: seaborn
Requires-Dist: segtools
Requires-Dist: snakemake
Requires-Dist: pybedtools
